.hgignore
CHANGES.txt
LICENSE.txt
MANIFEST.in
README.txt
bootstrap.sh
buildout.cfg
setup.py
js/__init__.py
js.vanderlee_colorpicker.egg-info/PKG-INFO
js.vanderlee_colorpicker.egg-info/SOURCES.txt
js.vanderlee_colorpicker.egg-info/dependency_links.txt
js.vanderlee_colorpicker.egg-info/entry_points.txt
js.vanderlee_colorpicker.egg-info/namespace_packages.txt
js.vanderlee_colorpicker.egg-info/not-zip-safe
js.vanderlee_colorpicker.egg-info/requires.txt
js.vanderlee_colorpicker.egg-info/top_level.txt
js/vanderlee_colorpicker/__init__.py
js/vanderlee_colorpicker/test_colorpicker.txt
js/vanderlee_colorpicker/resources/jquery.colorpicker.css
js/vanderlee_colorpicker/resources/jquery.colorpicker.js
js/vanderlee_colorpicker/resources/jquery.colorpicker.min.css
js/vanderlee_colorpicker/resources/jquery.colorpicker.min.js
js/vanderlee_colorpicker/resources/jquery.ui.colorpicker-cmyk-parser.js
js/vanderlee_colorpicker/resources/jquery.ui.colorpicker-cmyk-percentage-parser.js
js/vanderlee_colorpicker/resources/jquery.ui.colorpicker-crayola.js
js/vanderlee_colorpicker/resources/jquery.ui.colorpicker-pantone.js
js/vanderlee_colorpicker/resources/jquery.ui.colorpicker-ral-classic.js
js/vanderlee_colorpicker/resources/images/bar-alpha.png
js/vanderlee_colorpicker/resources/images/bar-opacity.png
js/vanderlee_colorpicker/resources/images/bar-pointer.png
js/vanderlee_colorpicker/resources/images/bar.png
js/vanderlee_colorpicker/resources/images/map-opacity.png
js/vanderlee_colorpicker/resources/images/map-pointer.png
js/vanderlee_colorpicker/resources/images/map.png
js/vanderlee_colorpicker/resources/images/preview-opacity.png
js/vanderlee_colorpicker/resources/images/ui-colorpicker.png
js/vanderlee_colorpicker/resources/images/128/bar-alpha.png
js/vanderlee_colorpicker/resources/images/128/bar.png
js/vanderlee_colorpicker/resources/images/128/map.png