Metadata-Version: 1.0
Name: js.vanderlee-colorpicker
Version: 1.0.9
Summary: Fanstatic packaging of vanderlee/colorpicker
Home-page: https://bitbucket.org/gocept/js.vanderlee_colorpicker
Author: gocept Developers
Author-email: mail@gocept.com
License: BSD
Platform: UNKNOWN
